{"total": 6794, "totalHits": 500, "hits": [{"id": 130175, "pageURL": "https://pixabay.com/videos/id-130175/", "type": "film", "tags": "flowers, field, woman, walk, stroll, nature", "duration": 10, "videos": {"large": {"url": "https://cdn.pixabay.com/video/2022/09/04/130175-746395232_large.mp4", "width": 1920, "height": 1080, "size": 7957068, "thumbnail": "https://cdn.pixabay.com/video/2022/09/04/130175-746395232_large.jpg"}, "medium": {"url": "https://cdn.pixabay.com/video/2022/09/04/130175-746395232_medium.mp4", "width": 1280, "height": 720, "size": 4081033, "thumbnail": "https://cdn.pixabay.com/video/2022/09/04/130175-746395232_medium.jpg"}, "small": {"url": "https://cdn.pixabay.com/video/2022/09/04/130175-746395232_small.mp4", "width": 960, "height": 540, "size": 2324666, "thumbnail": "https://cdn.pixabay.com/video/2022/09/04/130175-746395232_small.jpg"}, "tiny": {"url": "https://cdn.pixabay.com/video/2022/09/04/130175-746395232_tiny.mp4", "width": 640, "height": 360, "size": 1057493, "thumbnail": "https://cdn.pixabay.com/video/2022/09/04/130175-746395232_tiny.jpg"}}, "views": 39591, "downloads": 22371, "likes": 449, "comments": 72, "user_id": 29700033, "user": "magmelodies", "userImageURL": "https://cdn.pixabay.com/user/2022/09/04/04-42-29-97_250x250.jpg", "noAiTraining": false, "isAiGenerated": false, "isGRated": true, "isLowQuality": false, "userURL": "https://pixabay.com/users/29700033/", "name": "flowers, field, woman"}, {"id": 55974, "pageURL": "https://pixabay.com/videos/id-55974/", "type": "animation", "tags": "cow, spotty, cartoon, kawaii, hand drawn, anime, animal, character, bull, education, walking, loop, meadow, field, rural, walk, beautiful wallpaper, drawing, milk, farm, village, mill, background", "duration": 14, "videos": {"large": {"url": "https://cdn.pixabay.com/video/2020/11/09/55974-478348885_large.mp4", "width": 1920, "height": 1080, "size": 1611401, "thumbnail": "https://cdn.pixabay.com/video/2020/11/09/55974-478348885_large.jpg"}, "medium": {"url": "https://cdn.pixabay.com/video/2020/11/09/55974-478348885_medium.mp4", "width": 1280, "height": 720, "size": 1070580, "thumbnail": "https://cdn.pixabay.com/video/2020/11/09/55974-478348885_medium.jpg"}, "small": {"url": "https://cdn.pixabay.com/video/2020/11/09/55974-478348885_small.mp4", "width": 960, "height": 540, "size": 694443, "thumbnail": "https://cdn.pixabay.com/video/2020/11/09/55974-478348885_small.jpg"}, "tiny": {"url": "https://cdn.pixabay.com/video/2020/11/09/55974-478348885_tiny.mp4", "width": 640, "height": 360, "size": 617204, "thumbnail": "https://cdn.pixabay.com/video/2020/11/09/55974-478348885_tiny.jpg"}}, "views": 56912, "downloads": 24740, "likes": 242, "comments": 60, "user_id": 19032827, "user": "wodokolor", "userImageURL": "https://cdn.pixabay.com/user/2020/11/18/21-57-03-744_250x250.jpg", "noAiTraining": false, "isAiGenerated": false, "isGRated": true, "isLowQuality": false, "userURL": "https://pixabay.com/users/19032827/", "name": "cow, spotty, cartoon"}, {"id": 98814, "pageURL": "https://pixabay.com/videos/id-98814/", "type": "film", "tags": "dog, pet, walk, animal, field", "duration": 6, "videos": {"large": {"url": "https://cdn.pixabay.com/video/2021/11/24/98814-650523105_large.mp4", "width": 1920, "height": 1080, "size": 3829937, "thumbnail": "https://cdn.pixabay.com/video/2021/11/24/98814-650523105_large.jpg"}, "medium": {"url": "https://cdn.pixabay.com/video/2021/11/24/98814-650523105_medium.mp4", "width": 1280, "height": 720, "size": 2003902, "thumbnail": "https://cdn.pixabay.com/video/2021/11/24/98814-650523105_medium.jpg"}, "small": {"url": "https://cdn.pixabay.com/video/2021/11/24/98814-650523105_small.mp4", "width": 960, "height": 540, "size": 1252357, "thumbnail": "https://cdn.pixabay.com/video/2021/11/24/98814-650523105_small.jpg"}, "tiny": {"url": "https://cdn.pixabay.com/video/2021/11/24/98814-650523105_tiny.mp4", "width": 640, "height": 360, "size": 436951, "thumbnail": "https://cdn.pixabay.com/video/2021/11/24/98814-650523105_tiny.jpg"}}, "views": 20388, "downloads": 9944, "likes": 137, "comments": 18, "user_id": 17553994, "user": "jeffreygustin77", "userImageURL": "", "noAiTraining": false, "isAiGenerated": false, "isGRated": true, "isLowQuality": false, "userURL": "https://pixabay.com/users/17553994/", "name": "dog, pet, walk"}, {"id": 152203, "pageURL": "https://pixabay.com/videos/id-152203/", "type": "film", "tags": "man, stairs, walk, hike, travel, backpacker, nature, shiva, india", "duration": 8, "videos": {"large": {"url": "https://cdn.pixabay.com/video/2023/02/25/152203-802335648_large.mp4", "width": 1920, "height": 1080, "size": 3769119, "thumbnail": "https://cdn.pixabay.com/video/2023/02/25/152203-802335648_large.jpg"}, "medium": {"url": "https://cdn.pixabay.com/video/2023/02/25/152203-802335648_medium.mp4", "width": 1280, "height": 720, "size": 1936215, "thumbnail": "https://cdn.pixabay.com/video/2023/02/25/152203-802335648_medium.jpg"}, "small": {"url": "https://cdn.pixabay.com/video/2023/02/25/152203-802335648_small.mp4", "width": 960, "height": 540, "size": 1206874, "thumbnail": "https://cdn.pixabay.com/video/2023/02/25/152203-802335648_small.jpg"}, "tiny": {"url": "https://cdn.pixabay.com/video/2023/02/25/152203-802335648_tiny.mp4", "width": 640, "height": 360, "size": 655198, "thumbnail": "https://cdn.pixabay.com/video/2023/02/25/152203-802335648_tiny.jpg"}}, "views": 31798, "downloads": 15986, "likes": 116, "comments": 14, "user_id": 31542246, "user": "u_87zyvw82yc", "userImageURL": "https://cdn.pixabay.com/user/2023/02/25/18-04-29-702_250x250.jpg", "noAiTraining": false, "isAiGenerated": false, "isGRated": true, "isLowQuality": false, "userURL": "https://pixabay.com/users/31542246/", "name": "man, stairs, walk"}, {"id": 136985, "pageURL": "https://pixabay.com/videos/id-136985/", "type": "film", "tags": "village, field, nature, sky, asia, northeast, thailand", "duration": 13, "videos": {"large": {"url": "https://cdn.pixabay.com/video/2022/10/29/136985-765457987_large.mp4", "width": 1920, "height": 1080, "size": 9716847, "thumbnail": "https://cdn.pixabay.com/video/2022/10/29/136985-765457987_large.jpg"}, "medium": {"url": "https://cdn.pixabay.com/video/2022/10/29/136985-765457987_medium.mp4", "width": 1280, "height": 720, "size": 5439722, "thumbnail": "https://cdn.pixabay.com/video/2022/10/29/136985-765457987_medium.jpg"}, "small": {"url": "https://cdn.pixabay.com/video/2022/10/29/136985-765457987_small.mp4", "width": 960, "height": 540, "size": 3244907, "thumbnail": "https://cdn.pixabay.com/video/2022/10/29/136985-765457987_small.jpg"}, "tiny": {"url": "https://cdn.pixabay.com/video/2022/10/29/136985-765457987_tiny.mp4", "width": 640, "height": 360, "size": 1700448, "thumbnail": "https://cdn.pixabay.com/video/2022/10/29/136985-765457987_tiny.jpg"}}, "views": 8524, "downloads": 4725, "likes": 35, "comments": 4, "user_id": 30741353, "user": "judasboyz", "userImageURL": "https://cdn.pixabay.com/user/2022/10/20/16-09-32-445_250x250.jpg", "noAiTraining": false, "isAiGenerated": false, "isGRated": true, "isLowQuality": false, "userURL": "https://pixabay.com/users/30741353/", "name": "village, field, nature"}, {"id": 98830, "pageURL": "https://pixabay.com/videos/id-98830/", "type": "film", "tags": "dog, pet, animal, walk, field", "duration": 8, "videos": {"large": {"url": "https://cdn.pixabay.com/video/2021/11/24/98830-650523154_large.mp4", "width": 1920, "height": 1080, "size": 5235900, "thumbnail": "https://cdn.pixabay.com/video/2021/11/24/98830-650523154_large.jpg"}, "medium": {"url": "https://cdn.pixabay.com/video/2021/11/24/98830-650523154_medium.mp4", "width": 1280, "height": 720, "size": 2799524, "thumbnail": "https://cdn.pixabay.com/video/2021/11/24/98830-650523154_medium.jpg"}, "small": {"url": "https://cdn.pixabay.com/video/2021/11/24/98830-650523154_small.mp4", "width": 960, "height": 540, "size": 1671305, "thumbnail": "https://cdn.pixabay.com/video/2021/11/24/98830-650523154_small.jpg"}, "tiny": {"url": "https://cdn.pixabay.com/video/2021/11/24/98830-650523154_tiny.mp4", "width": 640, "height": 360, "size": 575556, "thumbnail": "https://cdn.pixabay.com/video/2021/11/24/98830-650523154_tiny.jpg"}}, "views": 9199, "downloads": 4998, "likes": 59, "comments": 4, "user_id": 17553994, "user": "jeffreygustin77", "userImageURL": "", "noAiTraining": false, "isAiGenerated": false, "isGRated": true, "isLowQuality": false, "userURL": "https://pixabay.com/users/17553994/", "name": "dog, pet, animal"}, {"id": 98815, "pageURL": "https://pixabay.com/videos/id-98815/", "type": "film", "tags": "dog, pet, walk, animal, field", "duration": 9, "videos": {"large": {"url": "https://cdn.pixabay.com/video/2021/11/24/98815-650523108_large.mp4", "width": 1920, "height": 1080, "size": 6182266, "thumbnail": "https://cdn.pixabay.com/video/2021/11/24/98815-650523108_large.jpg"}, "medium": {"url": "https://cdn.pixabay.com/video/2021/11/24/98815-650523108_medium.mp4", "width": 1280, "height": 720, "size": 3221010, "thumbnail": "https://cdn.pixabay.com/video/2021/11/24/98815-650523108_medium.jpg"}, "small": {"url": "https://cdn.pixabay.com/video/2021/11/24/98815-650523108_small.mp4", "width": 960, "height": 540, "size": 1987885, "thumbnail": "https://cdn.pixabay.com/video/2021/11/24/98815-650523108_small.jpg"}, "tiny": {"url": "https://cdn.pixabay.com/video/2021/11/24/98815-650523108_tiny.mp4", "width": 640, "height": 360, "size": 706225, "thumbnail": "https://cdn.pixabay.com/video/2021/11/24/98815-650523108_tiny.jpg"}}, "views": 11837, "downloads": 6303, "likes": 90, "comments": 7, "user_id": 17553994, "user": "jeffreygustin77", "userImageURL": "", "noAiTraining": false, "isAiGenerated": false, "isGRated": true, "isLowQuality": false, "userURL": "https://pixabay.com/users/17553994/", "name": "dog, pet, walk"}, {"id": 53042, "pageURL": "https://pixabay.com/videos/id-53042/", "type": "film", "tags": "river, landscape, village, fields", "duration": 60, "videos": {"large": {"url": "https://cdn.pixabay.com/video/2020/10/22/53042-472531783_large.mp4", "width": 3840, "height": 2160, "size": 183538933, "thumbnail": "https://cdn.pixabay.com/video/2020/10/22/53042-472531783_large.jpg"}, "medium": {"url": "https://cdn.pixabay.com/video/2020/10/22/53042-472531783_medium.mp4", "width": 2560, "height": 1440, "size": 101073168, "thumbnail": "https://cdn.pixabay.com/video/2020/10/22/53042-472531783_medium.jpg"}, "small": {"url": "https://cdn.pixabay.com/video/2020/10/22/53042-472531783_small.mp4", "width": 1920, "height": 1080, "size": 43464588, "thumbnail": "https://cdn.pixabay.com/video/2020/10/22/53042-472531783_small.jpg"}, "tiny": {"url": "https://cdn.pixabay.com/video/2020/10/22/53042-472531783_tiny.mp4", "width": 1280, "height": 720, "size": 22761937, "thumbnail": "https://cdn.pixabay.com/video/2020/10/22/53042-472531783_tiny.jpg"}}, "views": 14853, "downloads": 7252, "likes": 102, "comments": 12, "user_id": 16788253, "user": "dlabiebrzy", "userImageURL": "https://cdn.pixabay.com/user/2020/06/07/18-46-53-333_250x250.png", "noAiTraining": false, "isAiGenerated": false, "isGRated": true, "isLowQuality": false, "userURL": "https://pixabay.com/users/16788253/", "name": "river, landscape, village"}]}