{"total": 1796, "totalHits": 500, "hits": [{"id": 2365203, "pageURL": "https://pixabay.com/photos/man-steps-building-business-male-2365203/", "type": "photo", "tags": "man, steps, building, business, male, businessman, person, human, people, stairs, design, young, men, lifestyle, street, success, staircase, guy, work, professional, black, career, adult, suit, care, gray businessman, gray care", "previewURL": "https://cdn.pixabay.com/photo/2017/06/02/03/34/man-2365203_150.jpg", "previewWidth": 100, "previewHeight": 150, "webformatURL": "https://pixabay.com/get/gf2e06b859c848cf055c52cfb97598c284a69a7b210345c979d5b7e88b1ebd26651702a291f80d4015358e0d6cf28e783d37df738800b78bf167c10765d60896f_640.jpg", "webformatWidth": 426, "webformatHeight": 640, "largeImageURL": "https://pixabay.com/get/ga63e2952a31a9d4b53989a409be55af74a49d75677b2eb4d2a7622329e2056ac2dc6062aa0f1e8f4488f9bdc007c7db255c0f716278a9c357cf912ae700ecc7d_1280.jpg", "imageWidth": 3456, "imageHeight": 5184, "imageSize": 4985270, "views": 1841, "downloads": 672, "collections": 99, "likes": 14, "comments": 0, "user_id": 2974667, "user": "osullc2015", "userImageURL": "", "noAiTraining": false, "isAiGenerated": false, "isGRated": true, "isLowQuality": true, "userURL": "https://pixabay.com/users/2974667/", "name": "man, steps, building"}, {"id": 4951644, "pageURL": "https://pixabay.com/photos/fashion-male-man-corporate-4951644/", "type": "photo", "tags": "fashion, male, man, corporate, business, businessman, boss, senior, mature, executive, human, adult, face, people, young, confident, model, person, portrait, professional, success, work, man, man, businessman, businessman, businessman, boss, boss, human, people, people, people, professional, professional, professional, professional, professional, success, success, success", "previewURL": "https://cdn.pixabay.com/photo/2020/03/20/18/52/fashion-4951644_150.jpg", "previewWidth": 100, "previewHeight": 150, "webformatURL": "https://pixabay.com/get/g30b7a17d25a8074fc92720c39d3e97ab8fc0198af6b0c3cb85fb3b7d7b2af908764e7695deb99a816ee4e66e8c48430eefed24da04a92cade787b6455b953e0c_640.jpg", "webformatWidth": 427, "webformatHeight": 640, "largeImageURL": "https://pixabay.com/get/g7318149dce1b6156fb0c2835a92f18a86b9e09de84af250ffb6746a23aa0b413286151a00c59910320d6fe83abbc6ecb97262edec0321f82a6aee22f552f6df8_1280.jpg", "imageWidth": 3859, "imageHeight": 5788, "imageSize": 3227001, "views": 95531, "downloads": 87249, "collections": 76, "likes": 61, "comments": 5, "user_id": 15648905, "user": "kaziminmizan", "userImageURL": "https://cdn.pixabay.com/user/2025/01/19/10-16-54-710_250x250.jpg", "noAiTraining": false, "isAiGenerated": false, "isGRated": true, "isLowQuality": false, "userURL": "https://pixabay.com/users/15648905/", "name": "fashion, male, man"}, {"id": 4599846, "pageURL": "https://pixabay.com/photos/black-businessman-black-professional-4599846/", "type": "photo", "tags": "black businessman, black professional, professional, success, young, corporate, male, men, man, portrait, businessman, modern, confident, boss, work, attractive, career, executive, african american businessmen, specialist, successful, outfit, suit, black male professional, management, black businessman, black businessman, black businessman, black businessman, black businessman, black professional, businessman, boss, suit", "previewURL": "https://cdn.pixabay.com/photo/2019/11/03/23/27/black-businessman-4599846_150.jpg", "previewWidth": 100, "previewHeight": 150, "webformatURL": "https://pixabay.com/get/g7228b20e41b7b23fdf46d8bb0dddb74546acf6816c1cae8b10316d0c12ef1ff8242aec7b47206a472c3fd5127ad4769cc5e1812ee4bde6471873f5dfc739f53c_640.jpg", "webformatWidth": 426, "webformatHeight": 640, "largeImageURL": "https://pixabay.com/get/gcad21608f4150f36e9b31542e9a45ea59c5096aef8e2f96f1c3788765a00608d4d2f8c1798944f806eb7cd565814caa8bf920d7514ea43f41ad72cd10a7197b5_1280.jpg", "imageWidth": 3456, "imageHeight": 5184, "imageSize": 3079338, "views": 15434, "downloads": 11846, "collections": 720, "likes": 47, "comments": 6, "user_id": 14025988, "user": "elsimage", "userImageURL": "https://cdn.pixabay.com/user/2024/06/17/21-33-45-912_250x250.png", "noAiTraining": true, "isAiGenerated": false, "isGRated": true, "isLowQuality": false, "userURL": "https://pixabay.com/users/14025988/", "name": "black businessman, black professional, professional"}, {"id": 5257477, "pageURL": "https://pixabay.com/photos/sculpture-businessman-banker-5257477/", "type": "photo", "tags": "sculpture, businessman, banker, stock exchange, business, success, boss, office, money, banker, banker, banker, banker, banker", "previewURL": "https://cdn.pixabay.com/photo/2020/06/04/06/34/sculpture-5257477_150.jpg", "previewWidth": 100, "previewHeight": 150, "webformatURL": "https://pixabay.com/get/g53841d846ecfeea8739d6f2e75f3d09eee9ac46c4b5fbebf693593d4e01b3e6868d5803d699987223ed73790a380ad159a11b17dea224012161034ba19483768_640.jpg", "webformatWidth": 427, "webformatHeight": 640, "largeImageURL": "https://pixabay.com/get/g9599029e73385912aff734e9908ffdf82acee1227fe9b66ea5fa73127ab2caddb55697ee0c5e4a8ff77ff3d012b0f9bc0cb2b5b9c3422f352aaa3f61ea957bcf_1280.jpg", "imageWidth": 4016, "imageHeight": 6016, "imageSize": 5257274, "views": 2586, "downloads": 2198, "collections": 46, "likes": 6, "comments": 3, "user_id": 12138562, "user": "wal_172619", "userImageURL": "https://cdn.pixabay.com/user/2024/02/21/10-05-57-663_250x250.jpg", "noAiTraining": true, "isAiGenerated": false, "isGRated": true, "isLowQuality": false, "userURL": "https://pixabay.com/users/12138562/", "name": "sculpture, businessman, banker"}, {"id": 7509394, "pageURL": "https://pixabay.com/photos/stair-windows-glass-door-net-7509394/", "type": "photo", "tags": "stair, windows, glass door, net, yellow, blue, skyscrapers, minimalism, tran thang nhat, 5 plus english", "previewURL": "https://cdn.pixabay.com/photo/2022/10/09/14/57/stair-7509394_150.jpg", "previewWidth": 100, "previewHeight": 150, "webformatURL": "https://pixabay.com/get/g9c23eaf2278466a8554658f812d5eb369158d28a71adf75a72bfb3f43bd4b1bdd2e10e7b7d91df53d5de2443f451c9f62bacb7346fa5b8b5b39c9928a754185e_640.jpg", "webformatWidth": 426, "webformatHeight": 640, "largeImageURL": "https://pixabay.com/get/g51e9c0b4cb7f586b53a43a5633b7601c5bdca94ccc7a1b8e68aacab14733f7bfb215b56d97fdc93045d4d6ef5034e9429ad58157853bbef040aedf826fb2bfda_1280.jpg", "imageWidth": 2992, "imageHeight": 4500, "imageSize": 2146804, "views": 25873, "downloads": 14966, "collections": 65, "likes": 72, "comments": 5, "user_id": 26199248, "user": "Pix-Off", "userImageURL": "", "noAiTraining": false, "isAiGenerated": false, "isGRated": true, "isLowQuality": false, "userURL": "https://pixabay.com/users/26199248/", "name": "stair, windows, glass door"}, {"id": 5262122, "pageURL": "https://pixabay.com/photos/men-portrait-man-businessman-black-5262122/", "type": "photo", "tags": "men, portrait, man, businessman, black, male, professional, young, success", "previewURL": "https://cdn.pixabay.com/photo/2020/06/05/08/46/men-5262122_150.jpg", "previewWidth": 100, "previewHeight": 150, "webformatURL": "https://pixabay.com/get/ga1ae13855e4d7e0e7c83bd6f47b97ff8fc55eea29cef25d2d8c0af30183766819137fa42dfdb3e03bef526875e3e7177d0a027c22c3be57330389c088f5c41ca_640.jpg", "webformatWidth": 427, "webformatHeight": 640, "largeImageURL": "https://pixabay.com/get/g2edd00e6d047876fb99b91cfda8da6c9a8a06066011b3bd06ac01f1768c238d62c25788d9c868330fbce2989430009e03b9d78825082c7e4f54648b12f274be4_1280.jpg", "imageWidth": 4016, "imageHeight": 6016, "imageSize": 3443164, "views": 653, "downloads": 413, "collections": 37, "likes": 1, "comments": 0, "user_id": 12007965, "user": "HuyNgan", "userImageURL": "https://cdn.pixabay.com/user/2021/03/25/04-44-54-278_250x250.jpg", "noAiTraining": false, "isAiGenerated": false, "isGRated": true, "isLowQuality": false, "userURL": "https://pixabay.com/users/12007965/", "name": "men, portrait, man"}, {"id": 4599849, "pageURL": "https://pixabay.com/photos/black-businessman-black-professional-4599849/", "type": "photo", "tags": "black businessman, black professional, professional, success, young, corporate, male, men, man, portrait, businessman, modern, confident, boss, work, attractive, career, executive, african american businessmen, specialist, successful, outfit, suit, black male professional, management, black business, black work, black company, black management, black businessman, black businessman, black businessman, black professional, black professional, black professional, professional, professional, businessman, boss, boss, boss, boss, boss, executive, executive", "previewURL": "https://cdn.pixabay.com/photo/2019/11/03/23/28/black-businessman-4599849_150.jpg", "previewWidth": 100, "previewHeight": 150, "webformatURL": "https://pixabay.com/get/gc4b8f08d97284a4c2c0e0733a3e85f7144b3eb1d378885efb0a65e71f9d0ca95a42a33d3ca8ce2bafb2c322c779b0fe48179679b24cd4eb1ff5182db2fcbfc1d_640.jpg", "webformatWidth": 426, "webformatHeight": 640, "largeImageURL": "https://pixabay.com/get/gbd0d484360452ecb3541af2077dce6b3ba0d6c571a339af0f42001ca311aca53d1536f2a26e8472596a0177b4b010749e81f59c2c852cadc984d402492297b03_1280.jpg", "imageWidth": 3456, "imageHeight": 5184, "imageSize": 4369727, "views": 16541, "downloads": 13437, "collections": 641, "likes": 51, "comments": 2, "user_id": 14025988, "user": "elsimage", "userImageURL": "https://cdn.pixabay.com/user/2024/06/17/21-33-45-912_250x250.png", "noAiTraining": true, "isAiGenerated": false, "isGRated": true, "isLowQuality": false, "userURL": "https://pixabay.com/users/14025988/", "name": "black businessman, black professional, professional"}, {"id": 2911331, "pageURL": "https://pixabay.com/photos/man-fashion-businessman-suit-2911331/", "type": "photo", "tags": "man, fashion, businessman, suit, handsome, attractive, charming, stylish, guy, male, model, pose, portrait, corporate, adult, elegant, lifestyle, face, professional, men, happy, clothing, modern, success, style, boss, successful, business, confident, person, manager, outfit, profession, leadership, hairstyle, haircut, tie, fine-looking, human, standing, clothes, formal, businessman, businessman, businessman, businessman, businessman, suit, suit, suit, handsome, professional, men, men, boss, manager, manager", "previewURL": "https://cdn.pixabay.com/photo/2017/11/02/14/26/man-2911331_150.jpg", "previewWidth": 100, "previewHeight": 150, "webformatURL": "https://pixabay.com/get/g6e75cef92c7214d63e836ba0675f31f778c1b343b760d9b8110e4124c54b51dc912cc2b50fb12574977c5b20a94bae720e9d193fc32e32663d0963bdb4ce1951_640.jpg", "webformatWidth": 427, "webformatHeight": 640, "largeImageURL": "https://pixabay.com/get/g234579ad5c152e8ee78d1b83340448ec107c08d8473c8631ecac48259df0678c8c78a2b2f08ddc4f5975c2cfdf3296a7a1e45bd9a14ae0163507faaad4d9d2c2_1280.jpg", "imageWidth": 2832, "imageHeight": 4240, "imageSize": 2283634, "views": 30184, "downloads": 21386, "collections": 958, "likes": 74, "comments": 7, "user_id": 4597881, "user": "RoyalAnwar", "userImageURL": "https://cdn.pixabay.com/user/2018/04/01/06-25-38-399_250x250.jpeg", "noAiTraining": false, "isAiGenerated": false, "isGRated": true, "isLowQuality": false, "userURL": "https://pixabay.com/users/4597881/", "name": "man, fashion, businessman"}, {"id": 4599851, "pageURL": "https://pixabay.com/photos/black-businessman-black-professional-4599851/", "type": "photo", "tags": "black businessman, black professional, professional, success, young, corporate, male, men, man, portrait, businessman, modern, confident, boss, work, attractive, career, executive, african american businessmen, specialist, successful, outfit, suit, black male professional, management", "previewURL": "https://cdn.pixabay.com/photo/2019/11/03/23/28/black-businessman-4599851_150.jpg", "previewWidth": 100, "previewHeight": 150, "webformatURL": "https://pixabay.com/get/g57cefa4d7e356127cf951e5164aa780cee4567e8c827201216ed03af353c3fb6a87bff4a96fc288c9726c876cb6ec746d7560e1a08b22acb6e348b3a7ad1a76b_640.jpg", "webformatWidth": 426, "webformatHeight": 640, "largeImageURL": "https://pixabay.com/get/g759a9e4e66fdc555ac37c0820fa864659c020dba66d612f8a5a8feac38d3ae7305d15528475a03b2813892ab153402d1e82990e2603112913dda3ca471da65fa_1280.jpg", "imageWidth": 3456, "imageHeight": 5184, "imageSize": 3960189, "views": 7019, "downloads": 5445, "collections": 247, "likes": 21, "comments": 0, "user_id": 14025988, "user": "elsimage", "userImageURL": "https://cdn.pixabay.com/user/2024/06/17/21-33-45-912_250x250.png", "noAiTraining": true, "isAiGenerated": false, "isGRated": true, "isLowQuality": false, "userURL": "https://pixabay.com/users/14025988/", "name": "black businessman, black professional, professional"}, {"id": 4599850, "pageURL": "https://pixabay.com/photos/black-businessman-black-professional-4599850/", "type": "photo", "tags": "black businessman, black professional, professional, success, young, corporate, male, men, man, portrait, businessman, modern, confident, boss, work, attractive, career, executive, african american businessmen, specialist, successful, outfit, suit, black male professional, management, black businessman, black businessman, black businessman, black businessman, black businessman, black professional, success, male, businessman", "previewURL": "https://cdn.pixabay.com/photo/2019/11/03/23/28/black-businessman-4599850_150.jpg", "previewWidth": 100, "previewHeight": 150, "webformatURL": "https://pixabay.com/get/ged0539c2d0fb6bbbfe534b6f16ddf0e808885dc5d75c2781b40f00c9a69dd790da82329b6d3f42b94282537f691c3711b68c7291ee75680d56fa683846f6998f_640.jpg", "webformatWidth": 426, "webformatHeight": 640, "largeImageURL": "https://pixabay.com/get/g18f6359f812a82801696a88fb44a25de2d490852d995aaf93ebbbe2f360bbdf1d4e92a65dd775ffb1c9635e35a39934c854c7f2c678c769684107c074a3b4039_1280.jpg", "imageWidth": 3456, "imageHeight": 5184, "imageSize": 3859608, "views": 4811, "downloads": 3751, "collections": 158, "likes": 15, "comments": 1, "user_id": 14025988, "user": "elsimage", "userImageURL": "https://cdn.pixabay.com/user/2024/06/17/21-33-45-912_250x250.png", "noAiTraining": true, "isAiGenerated": false, "isGRated": true, "isLowQuality": false, "userURL": "https://pixabay.com/users/14025988/", "name": "black businessman, black professional, professional"}]}